exlog/__init__.py
exlog/exceptlog.py
exlog-1.0.3.dist-info/LICENSE
exlog-1.0.3.dist-info/METADATA
exlog-1.0.3.dist-info/WHEEL
exlog-1.0.3.dist-info/top_level.txt
exlog-1.0.3.dist-info/RECORD
