Metadata-Version: 2.1
Name: exlog
Version: 1.0.3
Summary: exception logging utilities
Home-page: https://github.com/yrom1/exception-logging
Author: yrom1
License: UNKNOWN
Platform: UNKNOWN
Classifier: Programming Language :: Python :: 3
Classifier: License :: OSI Approved :: MIT License
Classifier: Operating System :: OS Independent
Requires-Python: >=3.6
License-File: LICENSE
Requires-Dist: mypy-extensions
Requires-Dist: backports.zoneinfo ; python_version < "3.9"
